ebx_keypress/__init__.py
ebx_keypress-1.1.0.dist-info/LICENSE
ebx_keypress-1.1.0.dist-info/METADATA
ebx_keypress-1.1.0.dist-info/WHEEL
ebx_keypress-1.1.0.dist-info/top_level.txt
ebx_keypress-1.1.0.dist-info/RECORD
