Metadata-Version: 2.1
Name: ebx-keypress
Version: 1.1.0
Summary: Capture Keypress
Home-page: https://github.com/faustobranco/ebx_keypress
Author: Fausto Branco
Author-email: fausto.branco@gmail.com
License: UNKNOWN
Project-URL: Bug Tracker, https://github.com/faustobranco/ebx_keypress/issues
Platform: UNKNOWN
Classifier: Programming Language :: Python :: 3
Classifier: License :: OSI Approved :: MIT License
Classifier: Operating System :: OS Independent
Requires-Python: >=3.6
